{
  "id": "js-05",
  "title": "Strings",
  "content": "Strings can use single (' '), double (\" \"), or backtick (` ` for template literals) quotes.\n\nUseful methods:\n- length\n- toUpperCase()\n- slice()\n- split()\n- replace()\n\nTemplate literals allow embedding variables with ${}.",
  "codeExample": "let name = \"Alice\";\nconsole.log(`Hello ${name}!`);\nconsole.log(name.toUpperCase());",
  "trystarter": "let msg = \"javascript is cool\";\nconsole.log(msg.toUpperCase());",
  "language": "javascript"
}