{
  "id": "java-10",
  "title": "Exceptions & Error Handling",
  "content": "Use try/catch/finally to handle exceptions. Java differentiates checked (must be declared/handled) and unchecked (runtime) exceptions. Use throws in method signatures for checked exceptions.",
  "codeExample": "try {\n    int x = Integer.parseInt(\"abc\");\n} catch (NumberFormatException e) {\n    System.out.println(\"Bad number\");\n} finally {\n    System.out.println(\"Done\");\n}",
  "trystarter": "try { String s = null; s.length(); } catch (NullPointerException e) { System.out.println(\"null\"); }",
  "language": "java"
}